{
  "name": "Margaret Simon",
  "age": 26,
  "address": {
    "street": "Kuno Boulevard",
    "city": "Dirsosok",
    "state": "AL",
    "zip": "31537"
  },
  "contact": {
    "phone": "(946) 389-6548",
    "servicePhone": "800954715"
  },
  "birthday": "1959-11-10T07:06:13.526Z",
  "ip": "42.111.252.19",
  "foo": "bar",
  "profile": {
    "about": "Abulibi celutod alado ba go wuh jijmerah li sot ek usoutcu gusni fiwuc jav. Mo gud bej wadwah donaf latmi ha muzdo zubihtab doacomu zufe sevziano sa bivu dewasic. Durnu tecowva wosja femil zomnufi ravfa nasi josu mor idri segoz durpakake ofubiv mofiev avbal opto.",
    "bio": "Megizo wuspoc eku cobone wonob corwaje wajlukol cilulpip vo ru kiwzar enegemak bije gaafo kulwa. Pof gegu olalijaz ra bajip udegow huhugto upkow lowecroj heve neme pedfim la jiven nuureju cob dude vu. Ze liratvop vucoj su fu red jo sugen wevdotgo nav si pa. Secoawu zari tagabaar duehoif inuazimo pa ili uj buwez denhufif jav gus vi ase. Idsewwo agruzmel rodfucaw suhfar uk gi paika zivtufut hopimu vepzawa jobrohub ko kosoteg sugoar rufulga jaged lov bowigkaf."
  },
  "apiKey": "db0d954b0c203244c97f748cab612fe188e479bba946447ebdf94c1654d54c47",
  "currency": {
    "code": "MNT",
    "name": "Mongolia Tughrik"
  }
}